django_nativeshortuuidfield-1.4.11.dist-info/licenses/LICENSE
native_shortuuid/__init__.py
native_shortuuid/admin.py
native_shortuuid/apps.py
native_shortuuid/fields.py
native_shortuuid/validation.py
native_shortuuid/templates/admin/native_shortuuid/custom_change_list.html
native_shortuuid/templates/admin/native_shortuuid/native_shortuuid_search_form.html
native_shortuuid/templatetags/__init__.py
native_shortuuid/templatetags/native_shortuuid_tags.py
tests/__init__.py
tests/models.py
tests/test_settings.py
tests/test_shortuuid_field.py
django_nativeshortuuidfield-1.4.11.dist-info/METADATA
django_nativeshortuuidfield-1.4.11.dist-info/WHEEL
django_nativeshortuuidfield-1.4.11.dist-info/top_level.txt
django_nativeshortuuidfield-1.4.11.dist-info/RECORD
