Metadata-Version: 2.4
Name: django-nativeshortuuidfield
Version: 1.4.11
Summary: A decoder/encoder Field for uuid
Home-page: https://github.com/foundertherapy/django-nativeshortuuidfield
Author: Laith Abu Zainih
Author-email: Laith Abu Zainih <systems@foundertherapy.co>
Project-URL: Homepage, https://github.com/foundertherapy/django-nativeshortuuidfield
Keywords: shortuuid,uuid,nativeshortuuid
Classifier: Development Status :: 5 - Production/Stable
Classifier: Intended Audience :: Developers
Classifier: License :: OSI Approved :: MIT License
Classifier: Operating System :: OS Independent
Classifier: Topic :: Software Development :: Build Tools
Classifier: Topic :: Software Development :: Libraries :: Python Modules
Classifier: Topic :: Internet
Classifier: Programming Language :: Python :: 3
Classifier: Programming Language :: Python :: 3.10
Classifier: Programming Language :: Python :: 3 :: Only
Requires-Python: >=3.10
License-File: LICENSE
Requires-Dist: django>=4.1
Requires-Dist: djangorestframework>=3.13.1
Requires-Dist: django-shortuuidfield
Dynamic: author
Dynamic: home-page
Dynamic: license-file
Dynamic: requires-python
